<?xml version="1.0"?>
<!DOCTYPE xsa PUBLIC "-//LM Garshol//DTD XML Software Autoupdate 1.0//EN//XML" 
                     "http://www.garshol.priv.no/download/xsa/xsa.dtd">

<xsa>
  <vendor>
    <name>MetaStuff Ltd.</name>
    <email>info@dom4j.org</email>
    <url>http://dom4j.org</url>
  </vendor>

  <product id="dom4j">
    <name>dom4j</name>
    <version>0.3</version>
    <last-release>20010511</last-release>
    <info-url>http://dom4j.org/</info-url>
    <changes>
dom4j is an easy to use, open source Java library for working with XML.
The main new features of this release include:-

- improved XPath integration
- full JAXP, DOM, SAX and XSLT integration
- better I/O support
- new SAXValidator for validating Documents
- cleaner API
   </changes>
  </product>
</xsa>
